README.md
setup.cfg
setup.py
citrination_client/__init__.py
citrination_client/client.py
citrination_client.egg-info/PKG-INFO
citrination_client.egg-info/SOURCES.txt
citrination_client.egg-info/dependency_links.txt
citrination_client.egg-info/requires.txt
citrination_client.egg-info/top_level.txt
citrination_client/base/__init__.py
citrination_client/base/base_client.py
citrination_client/base/errors.py
citrination_client/base/response_handling.py
citrination_client/data/__init__.py
citrination_client/data/client.py
citrination_client/data/dataset.py
citrination_client/data/dataset_file.py
citrination_client/data/dataset_version.py
citrination_client/data/routes.py
citrination_client/data/upload_result.py
citrination_client/data/ingest/__init__.py
citrination_client/data/ingest/client.py
citrination_client/data/ingest/ingester.py
citrination_client/data/ingest/ingester_list.py
citrination_client/models/__init__.py
citrination_client/models/client.py
citrination_client/models/data_view_status.py
citrination_client/models/event.py
citrination_client/models/predicted_value.py
citrination_client/models/prediction_result.py
citrination_client/models/projection.py
citrination_client/models/routes.py
citrination_client/models/service_status.py
citrination_client/models/tsne.py
citrination_client/models/columns/__init__.py
citrination_client/models/columns/alloy_composition.py
citrination_client/models/columns/base.py
citrination_client/models/columns/categorical.py
citrination_client/models/columns/column_factory.py
citrination_client/models/columns/descriptor_converter.py
citrination_client/models/columns/formulation.py
citrination_client/models/columns/inorganic_chemical_formula.py
citrination_client/models/columns/integer.py
citrination_client/models/columns/organic_chemical_formula.py
citrination_client/models/columns/real.py
citrination_client/models/columns/vector.py
citrination_client/models/design/__init__.py
citrination_client/models/design/design_results.py
citrination_client/models/design/design_run.py
citrination_client/models/design/process_status.py
citrination_client/models/design/target.py
citrination_client/models/design/constraints/__init__.py
