Metadata-Version: 2.1
Name: citrination-client
Version: 6.5.0
Summary: Python client for accessing the Citrination api
Home-page: http://github.com/CitrineInformatics/python-citrination-client
License: UNKNOWN
Platform: UNKNOWN
Provides-Extra: dev
Provides-Extra: test
